fpgalab4_fsm.srcs/sources_1/imports/FPGALab4/library.v
// dffe: D-type flip-flop with enable
//
// q      (output) - Current value of flip flop
// d      (input)  - Next value of flip flop
// clk    (input)  - Clock (positive edge-sensitive)
// enable (input)  - Load new value? (yes = 1, no = 0)
// reset  (input)  - Asynchronous reset   (reset =  1)
//
module dffe(q, d, clk, enable, reset);
   output q;
   reg    q;
   input  d;
   input  clk, enable, reset;

   always@(reset)
     if (reset == 1'b1)
       q <= 0;

   always@(posedge clk)
     if ((reset == 1'b0) && (enable == 1'b1))
       q <= d;
endmodule // dffe

// muxNv: N-input mux
module mux2v(out, A, B, sel);

   parameter
     width = 32;
   
   output [width-1:0] out;
   input  [width-1:0] A, B;
   input 	      sel;

   wire [width-1:0] temp1 = ({width{(!sel)}} & A);
   wire [width-1:0] temp2 = ({width{(sel)}} & B);
   assign out = temp1 | temp2;

endmodule // mux2v

module mux3v(out, A, B, C, sel);

   parameter
     width = 32;
   
   output [width-1:0] out;
   input  [width-1:0] A, B, C;
   input  [1:0]	      sel;
   wire   [width-1:0] wAB;
   
   mux2v #(width) mAB (wAB, A, B, sel[0]);
   mux2v #(width) mfinal (out, wAB, C, sel[1]);

endmodule // mux3v

module mux4v(out, A, B, C, D, sel);

   parameter
     width = 32;
   
   output [width-1:0] out;
   input  [width-1:0] A, B, C, D;
   input  [1:0]	      sel;
   wire   [width-1:0] wAB, wCD;
   
   mux2v #(width) mAB (wAB, A, B, sel[0]);
   mux2v #(width) mCD (wCD, C, D, sel[0]);
   mux2v #(width) mfinal (out, wAB, wCD, sel[1]);

endmodule // mux4v

module mux16v(out, A, B, C, D, E, F, G, H, I, J, K, L, M, N, O, P, sel);

   parameter
     width = 32;
   
   output [width-1:0] out;
   input [width-1:0]  A, B, C, D, E, F, G, H, I, J, K, L, M, N, O, P;
   input [3:0] 	      sel;

   wire [width-1:0]   wAB, wCD, wEF, wGH, wIJ, wKL, wMN, wOP;
   wire [width-1:0]   wABCD, wEFGH, wIJKL, wMNOP;
   wire [width-1:0]   wABCDEFGH, wIJKLMNOP;
   
   mux2v #(width)  mAB (wAB, A, B, sel[0]);
   mux2v #(width)  mCD (wCD, C, D, sel[0]);
   mux2v #(width)  mEF (wEF, E, F, sel[0]);
   mux2v #(width)  mGH (wGH, G, H, sel[0]);
   mux2v #(width)  mIJ (wIJ, I, J, sel[0]);
   mux2v #(width)  mKL (wKL, K, L, sel[0]);
   mux2v #(width)  mMN (wMN, M, N, sel[0]);
   mux2v #(width)  mOP (wOP, O, P, sel[0]);

   mux2v #(width)  mABCD (wABCD, wAB, wCD, sel[1]);
   mux2v #(width)  mEFGH (wEFGH, wEF, wGH, sel[1]);
   mux2v #(width)  mIJKL (wIJKL, wIJ, wKL, sel[1]);
   mux2v #(width)  mMNOP (wMNOP, wMN, wOP, sel[1]);

   mux2v #(width)  mABCDEFGH (wABCDEFGH, wABCD, wEFGH, sel[2]);
   mux2v #(width)  mIJKLMNOP (wIJKLMNOP, wIJKL, wMNOP, sel[2]);
   
   mux2v #(width)  mfinal (out, wABCDEFGH, wIJKLMNOP, sel[3]);

endmodule // mux16v

module mux32v(out, a, b, c, d, e, f, g, h, i, j, k, l, m, n, o, p, 
	          A, B, C, D, E, F, G, H, I, J, K, L, M, N, O, P, sel);

   parameter
     width = 32;
   
   output [width-1:0] out;
   input [width-1:0]  a, b, c, d, e, f, g, h, i, j, k, l, m, n, o, p;
   input [width-1:0]  A, B, C, D, E, F, G, H, I, J, K, L, M, N, O, P;
   input [4:0] 	      sel;
   wire [width-1:0]   wUPPER, wlower;

   mux16v #(width) m0(wlower, a, b, c, d, e, f, g, h, i, j, k, l, m, n, o, p, sel[3:0]);
   mux16v #(width) m1(wUPPER, A, B, C, D, E, F, G, H, I, J, K, L, M, N, O, P, sel[3:0]);
   mux2v  #(width) mfinal (out, wlower, wUPPER, sel[4]);
   
endmodule // mux32v

fpgalab4_fsm.srcs/sources_1/imports/FPGALab4/register.v
// register: A register which may be reset to an arbirary value
//
// q      (output) - Current value of register
// d      (input)  - Next value of register
// clk    (input)  - Clock (positive edge-sensitive)
// enable (input)  - Load new value? (yes = 1, no = 0)
// reset  (input)  - Asynchronous reset    (reset = 1)
//
module register(q, d, clk, enable, reset);

    parameter
        width = 32,
        reset_value = 0;
 
    output [(width-1):0] q;
    reg    [(width-1):0] q;
    input  [(width-1):0] d;
    input                clk, enable, reset;
 
    always@(posedge clk) begin
      if ((reset == 1'b0) && (enable == 1'b1))
        q <= d;
      if (reset == 1'b1)
          q <= reset_value;
    end
endmodule // register

fpgalab4_fsm.srcs/sources_1/imports/FPGALab4/counter_natural.v
module counter_natural(out, reverse, pause, clk, reset);
	output [3:0] out;
	input reverse, pause, clk, reset;
	wire [3:0] Q, D, Q_next, next, next_above, increment;

	register #(4) counter(Q, D, clk, ~pause, reset);
	mux2v #(4) mux_dir(increment, 4'h1, 4'hf, reverse); 		// output 1 when direct = 0
	assign Q_next = (Q + increment);
	mux2v #(4) mux_out(next, Q_next, Q, pause);
	assign above_range = (Q == 4'd9) && ~reverse;
	assign below_range = (Q == 4'd0) && reverse;
	mux2v #(4) mux_above_range(next_above, next, 4'b0, above_range);
	mux2v #(4) mux_below_range(D, next_above, 4'd9, below_range);
	assign out = Q;
endmodule

fpgalab4_fsm.srcs/sim_1/imports/FPGALab4/counter_natural_tb.v
module counter_natural_test;

    reg reset, pause, reverse;                           // these are inputs to "circuit under test"
    reg       clk = 0;
    always #5 clk = !clk;
    wire [3:0] out;                        // use "reg" not "wire" so can assign a value
                                            // wires for the outputs of "circuit under test"

    counter_natural cn(out, reverse, pause, clk, reset);                        // the circuit under test
    
    initial begin                             // initial = run at beginning of simulation
                                              // begin/end = associate block with initial
 
        $dumpfile("counter_natural.vcd");                  // name of dump file to create
        $dumpvars(0, counter_natural_test);                 // record all signals of module "sc_test" and sub-modules
                                              // remember to change "sc_test" to the correct
                                              // module name when writing your own test benches
        
        // test all four input combinations
        // remember that 2 inputs means 2^2 = 4 combinations
        // 3 inputs would mean 2^3 = 8 combinations to test, and so on
        // this is very similar to the input columns of a truth table
        # 10;
        reverse = 1'b0;
        pause = 1'b0;
        reset = 1'b1;
        # 10;
        reverse = 1'b0;
        pause = 1'b0;
        reset = 1'b0;
        # 50
        pause = 1'b1;
        # 50
        pause = 1'b0;
        # 20
        reset = 1'b1;
        # 20
        reset = 1'b0;            
        # 200;
        reverse = 1'b1;
        # 200;


                     // set initial values and wait 10 time units
                     // change inputs and then wait 10 time units
                     // as above
        $finish;                              // end the simulation
    end                      
endmodule

fpgalab4_fsm.sim/sim_1/behav/counter_natural.vcd
$date
   Thu May  5 20:46:14 2016
$end
$version
  13.1
$end
$timescale
  1ps
$end
$scope module counter_natural_test $end
$var reg 1 ! reset $end
$var reg 1 " pause $end
$var reg 1 # reverse $end
$var reg 1 $ clk $end
$var wire 4 % out [3:0] $end
$scope module cn $end
$var wire 4 & out [3:0] $end
$var wire 1 ' reverse $end
$var wire 1 ( pause $end
$var wire 1 ) clk $end
$var wire 1 * reset $end
$var wire 4 + Q [3:0] $end
$var wire 4 , D [3:0] $end
$var wire 4 - Q_next [3:0] $end
$var wire 4 . next [3:0] $end
$var wire 4 / next_above [3:0] $end
$var wire 4 0 increment [3:0] $end
$var wire 1 1 above_range $end
$var wire 1 2 below_range $end
$scope module counter $end
$var reg 4 3 q [3:0] $end
$var wire 4 4 d [3:0] $end
$var wire 1 5 clk $end
$var wire 1 6 enable $end
$var wire 1 7 reset $end
$var parameter 32 8 width [31:0] $end
$var parameter 32 9 reset_value [31:0] $end
$upscope $end
$scope module mux_dir $end
$var wire 4 : out [3:0] $end
$var wire 4 ; A [3:0] $end
$var wire 4 < B [3:0] $end
$var wire 1 = sel $end
$var wire 4 > temp1 [3:0] $end
$var wire 4 ? temp2 [3:0] $end
$var parameter 32 @ width [31:0] $end
$upscope $end
$scope module mux_out $end
$var wire 4 A out [3:0] $end
$var wire 4 B A [3:0] $end
$var wire 4 C B [3:0] $end
$var wire 1 D sel $end
$var wire 4 E temp1 [3:0] $end
$var wire 4 F temp2 [3:0] $end
$var parameter 32 G width [31:0] $end
$upscope $end
$scope module mux_above_range $end
$var wire 4 H out [3:0] $end
$var wire 4 I A [3:0] $end
$var wire 4 J B [3:0] $end
$var wire 1 K sel $end
$var wire 4 L temp1 [3:0] $end
$var wire 4 M temp2 [3:0] $end
$var parameter 32 N width [31:0] $end
$upscope $end
$scope module mux_below_range $end
$var wire 4 O out [3:0] $end
$var wire 4 P A [3:0] $end
$var wire 4 Q B [3:0] $end
$var wire 1 R sel $end
$var wire 4 S temp1 [3:0] $end
$var wire 4 T temp2 [3:0] $end
$var parameter 32 U width [31:0] $end
$upscope $end
$upscope $end
$upscope $end
$enddefinitions $end
#0
$dumpvars
x!
x"
x#
0$
bx %
bx &
x'
x(
0)
x*
bx +
bx ,
bx -
bx .
bx /
bx 0
x1
x2
bx 3
bx 4
05
x6
x7
b100 8
b0 9
bx :
b1 ;
b1111 <
x=
b0x >
bx ?
b100 @
bx A
bx B
bx C
xD
bx E
bx F
b100 G
bx H
bx I
b0 J
xK
bx L
b0 M
b100 N
bx O
bx P
b1001 Q
xR
bx S
bx00x T
b100 U
$end
#5000
1$
1)
15
#10000
1!
0"
0#
0$
0'
0(
0)
1*
bx -
bx .
b1 0
x1
02
05
16
17
b1 :
0=
b1 >
b0 ?
bx A
bx B
0D
bx E
b0 F
bx I
xK
0R
bx S
b0 T
#15000
1$
b0 %
b0 &
1)
b0 +
b1 ,
b1 -
b1 .
b1 /
01
02
b0 3
b1 4
15
b1 A
b1 B
b0 C
b1 E
b0 F
b1 H
b1 I
0K
b1 L
b0 M
b1 O
b1 P
0R
b1 S
#20000
0!
0$
0)
0*
05
07
#25000
1$
b1 %
b1 &
1)
b1 +
b10 ,
b10 -
b10 .
b10 /
01
02
b1 3
b10 4
15
b10 A
b10 B
b1 C
b10 E
b0 F
b10 H
b10 I
0K
b10 L
b10 O
b10 P
0R
b10 S
#30000
0$
0)
05
#35000
1$
b10 %
b10 &
1)
b10 +
b11 ,
b11 -
b11 .
b11 /
01
02
b10 3
b11 4
15
b11 A
b11 B
b10 C
b11 E
b0 F
b11 H
b11 I
0K
b11 L
b11 O
b11 P
0R
b11 S
#40000
0$
0)
05
#45000
1$
b11 %
b11 &
1)
b11 +
b100 ,
b100 -
b100 .
b100 /
01
02
b11 3
b100 4
15
b100 A
b100 B
b11 C
b100 E
b0 F
b100 H
b100 I
0K
b100 L
b100 O
b100 P
0R
b100 S
#50000
0$
0)
05
#55000
1$
b100 %
b100 &
1)
b100 +
b101 ,
b101 -
b101 .
b101 /
01
02
b100 3
b101 4
15
b101 A
b101 B
b100 C
b101 E
b0 F
b101 H
b101 I
0K
b101 L
b101 O
b101 P
0R
b101 S
#60000
0$
0)
05
#65000
1$
b101 %
b101 &
1)
b101 +
b110 ,
b110 -
b110 .
b110 /
01
02
b101 3
b110 4
15
b110 A
b110 B
b101 C
b110 E
b0 F
b110 H
b110 I
0K
b110 L
b110 O
b110 P
0R
b110 S
#70000
1"
0$
1(
0)
b101 ,
b101 .
b101 /
b101 4
05
06
b101 A
1D
b0 E
b101 F
b101 H
b101 I
b101 L
b101 O
b101 P
b101 S
#75000
1$
1)
15
#80000
0$
0)
05
#85000
1$
1)
15
#90000
0$
0)
05
#95000
1$
1)
15
#100000
0$
0)
05
#105000
1$
1)
15
#110000
0$
0)
05
#115000
1$
1)
15
#120000
0"
0$
0(
0)
b110 ,
b110 .
b110 /
b110 4
05
16
b110 A
0D
b110 E
b0 F
b110 H
b110 I
b110 L
b110 O
b110 P
b110 S
#125000
1$
b110 %
b110 &
1)
b110 +
b111 ,
b111 -
b111 .
b111 /
01
02
b110 3
b111 4
15
b111 A
b111 B
b110 C
b111 E
b0 F
b111 H
b111 I
0K
b111 L
b111 O
b111 P
0R
b111 S
#130000
0$
0)
05
#135000
1$
b111 %
b111 &
1)
b111 +
b1000 ,
b1000 -
b1000 .
b1000 /
01
02
b111 3
b1000 4
15
b1000 A
b1000 B
b111 C
b1000 E
b0 F
b1000 H
b1000 I
0K
b1000 L
b1000 O
b1000 P
0R
b1000 S
#140000
1!
0$
0)
1*
05
17
#145000
1$
b0 %
b0 &
1)
b0 +
b1 ,
b1 -
b1 .
b1 /
01
02
b0 3
b1 4
15
b1 A
b1 B
b0 C
b1 E
b0 F
b1 H
b1 I
0K
b1 L
b1 O
b1 P
0R
b1 S
#150000
0$
0)
05
#155000
1$
1)
b0 3
15
#160000
0!
0$
0)
0*
05
07
#165000
1$
b1 %
b1 &
1)
b1 +
b10 ,
b10 -
b10 .
b10 /
01
02
b1 3
b10 4
15
b10 A
b10 B
b1 C
b10 E
b0 F
b10 H
b10 I
0K
b10 L
b10 O
b10 P
0R
b10 S
#170000
0$
0)
05
#175000
1$
b10 %
b10 &
1)
b10 +
b11 ,
b11 -
b11 .
b11 /
01
02
b10 3
b11 4
15
b11 A
b11 B
b10 C
b11 E
b0 F
b11 H
b11 I
0K
b11 L
b11 O
b11 P
0R
b11 S
#180000
0$
0)
05
#185000
1$
b11 %
b11 &
1)
b11 +
b100 ,
b100 -
b100 .
b100 /
01
02
b11 3
b100 4
15
b100 A
b100 B
b11 C
b100 E
b0 F
b100 H
b100 I
0K
b100 L
b100 O
b100 P
0R
b100 S
#190000
0$
0)
05
#195000
1$
b100 %
b100 &
1)
b100 +
b101 ,
b101 -
b101 .
b101 /
01
02
b100 3
b101 4
15
b101 A
b101 B
b100 C
b101 E
b0 F
b101 H
b101 I
0K
b101 L
b101 O
b101 P
0R
b101 S
#200000
0$
0)
05
#205000
1$
b101 %
b101 &
1)
b101 +
b110 ,
b110 -
b110 .
b110 /
01
02
b101 3
b110 4
15
b110 A
b110 B
b101 C
b110 E
b0 F
b110 H
b110 I
0K
b110 L
b110 O
b110 P
0R
b110 S
#210000
0$
0)
05
#215000
1$
b110 %
b110 &
1)
b110 +
b111 ,
b111 -
b111 .
b111 /
01
02
b110 3
b111 4
15
b111 A
b111 B
b110 C
b111 E
b0 F
b111 H
b111 I
0K
b111 L
b111 O
b111 P
0R
b111 S
#220000
0$
0)
05
#225000
1$
b111 %
b111 &
1)
b111 +
b1000 ,
b1000 -
b1000 .
b1000 /
01
02
b111 3
b1000 4
15
b1000 A
b1000 B
b111 C
b1000 E
b0 F
b1000 H
b1000 I
0K
b1000 L
b1000 O
b1000 P
0R
b1000 S
#230000
0$
0)
05
#235000
1$
b1000 %
b1000 &
1)
b1000 +
b1001 ,
b1001 -
b1001 .
b1001 /
01
02
b1000 3
b1001 4
15
b1001 A
b1001 B
b1000 C
b1001 E
b0 F
b1001 H
b1001 I
0K
b1001 L
b1001 O
b1001 P
0R
b1001 S
#240000
0$
0)
05
#245000
1$
b1001 %
b1001 &
1)
b1001 +
b0 ,
b1010 -
b1010 .
b0 /
11
02
b1001 3
b0 4
15
b1010 A
b1010 B
b1001 C
b1010 E
b0 F
b0 H
b1010 I
1K
b0 L
b0 M
b0 O
b0 P
0R
b0 S
#250000
0$
0)
05
#255000
1$
b0 %
b0 &
1)
b0 +
b1 ,
b1 -
b1 .
b1 /
01
02
b0 3
b1 4
15
b1 A
b1 B
b0 C
b1 E
b0 F
b1 H
b1 I
0K
b1 L
b0 M
b1 O
b1 P
0R
b1 S
#260000
0$
0)
05
#265000
1$
b1 %
b1 &
1)
b1 +
b10 ,
b10 -
b10 .
b10 /
01
02
b1 3
b10 4
15
b10 A
b10 B
b1 C
b10 E
b0 F
b10 H
b10 I
0K
b10 L
b10 O
b10 P
0R
b10 S
#270000
0$
0)
05
#275000
1$
b10 %
b10 &
1)
b10 +
b11 ,
b11 -
b11 .
b11 /
01
02
b10 3
b11 4
15
b11 A
b11 B
b10 C
b11 E
b0 F
b11 H
b11 I
0K
b11 L
b11 O
b11 P
0R
b11 S
#280000
0$
0)
05
#285000
1$
b11 %
b11 &
1)
b11 +
b100 ,
b100 -
b100 .
b100 /
01
02
b11 3
b100 4
15
b100 A
b100 B
b11 C
b100 E
b0 F
b100 H
b100 I
0K
b100 L
b100 O
b100 P
0R
b100 S
#290000
0$
0)
05
#295000
1$
b100 %
b100 &
1)
b100 +
b101 ,
b101 -
b101 .
b101 /
01
02
b100 3
b101 4
15
b101 A
b101 B
b100 C
b101 E
b0 F
b101 H
b101 I
0K
b101 L
b101 O
b101 P
0R
b101 S
#300000
0$
0)
05
#305000
1$
b101 %
b101 &
1)
b101 +
b110 ,
b110 -
b110 .
b110 /
01
02
b101 3
b110 4
15
b110 A
b110 B
b101 C
b110 E
b0 F
b110 H
b110 I
0K
b110 L
b110 O
b110 P
0R
b110 S
#310000
0$
0)
05
#315000
1$
b110 %
b110 &
1)
b110 +
b111 ,
b111 -
b111 .
b111 /
01
02
b110 3
b111 4
15
b111 A
b111 B
b110 C
b111 E
b0 F
b111 H
b111 I
0K
b111 L
b111 O
b111 P
0R
b111 S
#320000
0$
0)
05
#325000
1$
b111 %
b111 &
1)
b111 +
b1000 ,
b1000 -
b1000 .
b1000 /
01
02
b111 3
b1000 4
15
b1000 A
b1000 B
b111 C
b1000 E
b0 F
b1000 H
b1000 I
0K
b1000 L
b1000 O
b1000 P
0R
b1000 S
#330000
0$
0)
05
#335000
1$
b1000 %
b1000 &
1)
b1000 +
b1001 ,
b1001 -
b1001 .
b1001 /
01
02
b1000 3
b1001 4
15
b1001 A
b1001 B
b1000 C
b1001 E
b0 F
b1001 H
b1001 I
0K
b1001 L
b1001 O
b1001 P
0R
b1001 S
#340000
0$
0)
05
#345000
1$
b1001 %
b1001 &
1)
b1001 +
b0 ,
b1010 -
b1010 .
b0 /
11
02
b1001 3
b0 4
15
b1010 A
b1010 B
b1001 C
b1010 E
b0 F
b0 H
b1010 I
1K
b0 L
b0 M
b0 O
b0 P
0R
b0 S
#350000
0$
0)
05
#355000
1$
b0 %
b0 &
1)
b0 +
b1 ,
b1 -
b1 .
b1 /
01
02
b0 3
b1 4
15
b1 A
b1 B
b0 C
b1 E
b0 F
b1 H
b1 I
0K
b1 L
b0 M
b1 O
b1 P
0R
b1 S
#360000
1#
0$
1'
0)
b1001 ,
b1111 -
b1111 .
b1111 /
b1111 0
01
12
b1001 4
05
b1111 :
1=
b0 >
b1111 ?
b1111 A
b1111 B
b1111 E
b1111 H
b1111 I
0K
b1111 L
b1001 O
b1111 P
1R
b0 S
b1001 T
#365000
1$
b1001 %
b1001 &
1)
b1001 +
b1000 ,
b1000 -
b1000 .
b1000 /
01
02
b1001 3
b1000 4
15
b1000 A
b1000 B
b1001 C
b1000 E
b0 F
b1000 H
b1000 I
0K
b1000 L
b1000 O
b1000 P
0R
b1000 S
b0 T
#370000
0$
0)
05
#375000
1$
b1000 %
b1000 &
1)
b1000 +
b111 ,
b111 -
b111 .
b111 /
01
02
b1000 3
b111 4
15
b111 A
b111 B
b1000 C
b111 E
b0 F
b111 H
b111 I
0K
b111 L
b111 O
b111 P
0R
b111 S
#380000
0$
0)
05
#385000
1$
b111 %
b111 &
1)
b111 +
b110 ,
b110 -
b110 .
b110 /
01
02
b111 3
b110 4
15
b110 A
b110 B
b111 C
b110 E
b0 F
b110 H
b110 I
0K
b110 L
b110 O
b110 P
0R
b110 S
#390000
0$
0)
05
#395000
1$
b110 %
b110 &
1)
b110 +
b101 ,
b101 -
b101 .
b101 /
01
02
b110 3
b101 4
15
b101 A
b101 B
b110 C
b101 E
b0 F
b101 H
b101 I
0K
b101 L
b101 O
b101 P
0R
b101 S
#400000
0$
0)
05
#405000
1$
b101 %
b101 &
1)
b101 +
b100 ,
b100 -
b100 .
b100 /
01
02
b101 3
b100 4
15
b100 A
b100 B
b101 C
b100 E
b0 F
b100 H
b100 I
0K
b100 L
b100 O
b100 P
0R
b100 S
#410000
0$
0)
05
#415000
1$
b100 %
b100 &
1)
b100 +
b11 ,
b11 -
b11 .
b11 /
01
02
b100 3
b11 4
15
b11 A
b11 B
b100 C
b11 E
b0 F
b11 H
b11 I
0K
b11 L
b11 O
b11 P
0R
b11 S
#420000
0$
0)
05
#425000
1$
b11 %
b11 &
1)
b11 +
b10 ,
b10 -
b10 .
b10 /
01
02
b11 3
b10 4
15
b10 A
b10 B
b11 C
b10 E
b0 F
b10 H
b10 I
0K
b10 L
b10 O
b10 P
0R
b10 S
#430000
0$
0)
05
#435000
1$
b10 %
b10 &
1)
b10 +
b1 ,
b1 -
b1 .
b1 /
01
02
b10 3
b1 4
15
b1 A
b1 B
b10 C
b1 E
b0 F
b1 H
b1 I
0K
b1 L
b1 O
b1 P
0R
b1 S
#440000
0$
0)
05
#445000
1$
b1 %
b1 &
1)
b1 +
b0 ,
b0 -
b0 .
b0 /
01
02
b1 3
b0 4
15
b0 A
b0 B
b1 C
b0 E
b0 F
b0 H
b0 I
0K
b0 L
b0 O
b0 P
0R
b0 S
#450000
0$
0)
05
#455000
1$
b0 %
b0 &
1)
b0 +
b1001 ,
b1111 -
b1111 .
b1111 /
01
12
b0 3
b1001 4
15
b1111 A
b1111 B
b0 C
b1111 E
b0 F
b1111 H
b1111 I
0K
b1111 L
b1001 O
b1111 P
1R
b0 S
b1001 T
#460000
0$
0)
05
#465000
1$
b1001 %
b1001 &
1)
b1001 +
b1000 ,
b1000 -
b1000 .
b1000 /
01
02
b1001 3
b1000 4
15
b1000 A
b1000 B
b1001 C
b1000 E
b0 F
b1000 H
b1000 I
0K
b1000 L
b1000 O
b1000 P
0R
b1000 S
b0 T
#470000
0$
0)
05
#475000
1$
b1000 %
b1000 &
1)
b1000 +
b111 ,
b111 -
b111 .
b111 /
01
02
b1000 3
b111 4
15
b111 A
b111 B
b1000 C
b111 E
b0 F
b111 H
b111 I
0K
b111 L
b111 O
b111 P
0R
b111 S
#480000
0$
0)
05
#485000
1$
b111 %
b111 &
1)
b111 +
b110 ,
b110 -
b110 .
b110 /
01
02
b111 3
b110 4
15
b110 A
b110 B
b111 C
b110 E
b0 F
b110 H
b110 I
0K
b110 L
b110 O
b110 P
0R
b110 S
#490000
0$
0)
05
#495000
1$
b110 %
b110 &
1)
b110 +
b101 ,
b101 -
b101 .
b101 /
01
02
b110 3
b101 4
15
b101 A
b101 B
b110 C
b101 E
b0 F
b101 H
b101 I
0K
b101 L
b101 O
b101 P
0R
b101 S
#500000
0$
0)
05
#505000
1$
b101 %
b101 &
1)
b101 +
b100 ,
b100 -
b100 .
b100 /
01
02
b101 3
b100 4
15
b100 A
b100 B
b101 C
b100 E
b0 F
b100 H
b100 I
0K
b100 L
b100 O
b100 P
0R
b100 S
#510000
0$
0)
05
#515000
1$
b100 %
b100 &
1)
b100 +
b11 ,
b11 -
b11 .
b11 /
01
02
b100 3
b11 4
15
b11 A
b11 B
b100 C
b11 E
b0 F
b11 H
b11 I
0K
b11 L
b11 O
b11 P
0R
b11 S
#520000
0$
0)
05
#525000
1$
b11 %
b11 &
1)
b11 +
b10 ,
b10 -
b10 .
b10 /
01
02
b11 3
b10 4
15
b10 A
b10 B
b11 C
b10 E
b0 F
b10 H
b10 I
0K
b10 L
b10 O
b10 P
0R
b10 S
#530000
0$
0)
05
#535000
1$
b10 %
b10 &
1)
b10 +
b1 ,
b1 -
b1 .
b1 /
01
02
b10 3
b1 4
15
b1 A
b1 B
b10 C
b1 E
b0 F
b1 H
b1 I
0K
b1 L
b1 O
b1 P
0R
b1 S
#540000
0$
0)
05
#545000
1$
b1 %
b1 &
1)
b1 +
b0 ,
b0 -
b0 .
b0 /
01
02
b1 3
b0 4
15
b0 A
b0 B
b1 C
b0 E
b0 F
b0 H
b0 I
0K
b0 L
b0 O
b0 P
0R
b0 S
#550000
0$
0)
05
#555000
1$
b0 %
b0 &
1)
b0 +
b1001 ,
b1111 -
b1111 .
b1111 /
01
12
b0 3
b1001 4
15
b1111 A
b1111 B
b0 C
b1111 E
b0 F
b1111 H
b1111 I
0K
b1111 L
b1001 O
b1111 P
1R
b0 S
b1001 T
